{"contigLinks":[{"source":"EDGE_10","target":"EDGE_183"},{"source":"EDGE_10","target":"EDGE_55'"},{"source":"EDGE_10'","target":"EDGE_12"},{"source":"EDGE_31","target":"EDGE_177'"},{"source":"EDGE_31","target":"EDGE_216'"},{"source":"EDGE_31'","target":"EDGE_34"},{"source":"EDGE_3","target":"EDGE_136'"},{"source":"EDGE_3","target":"EDGE_1'"},{"source":"EDGE_3'","target":"EDGE_1"},{"source":"EDGE_3'","target":"EDGE_2"},{"source":"EDGE_22'","target":"EDGE_22'"},{"source":"EDGE_22","target":"EDGE_22"},{"source":"EDGE_23'","target":"EDGE_25"},{"source":"EDGE_23","target":"EDGE_63"},{"source":"EDGE_23","target":"EDGE_77"},{"source":"EDGE_23","target":"EDGE_77'"},{"source":"EDGE_23","target":"EDGE_76"},{"source":"EDGE_23","target":"EDGE_76'"},{"source":"EDGE_54","target":"EDGE_247'"},{"source":"EDGE_54'","target":"EDGE_52"},{"source":"EDGE_54'","target":"EDGE_53"},{"source":"EDGE_43","target":"EDGE_112"},{"source":"EDGE_43","target":"EDGE_113"},{"source":"EDGE_43'","target":"EDGE_45"},{"source":"EDGE_102'","target":"EDGE_101"},{"source":"EDGE_102'","target":"EDGE_69'"},{"source":"EDGE_102","target":"EDGE_160"},{"source":"EDGE_157","target":"EDGE_158'"},{"source":"EDGE_157","target":"EDGE_203"},{"source":"EDGE_157'","target":"EDGE_158"},{"source":"EDGE_157'","target":"EDGE_159"},{"source":"EDGE_161","target":"EDGE_190"},{"source":"EDGE_161'","target":"EDGE_162"},{"source":"EDGE_161'","target":"EDGE_98'"},{"source":"EDGE_156","target":"EDGE_178"},{"source":"EDGE_156","target":"EDGE_179"},{"source":"EDGE_156'","target":"EDGE_49'"},{"source":"EDGE_156'","target":"EDGE_169"},{"source":"EDGE_156'","target":"EDGE_169'"},{"source":"EDGE_175","target":"EDGE_37'"},{"source":"EDGE_175'","target":"EDGE_173"},{"source":"EDGE_175'","target":"EDGE_174"},{"source":"EDGE_168'","target":"EDGE_168'"},{"source":"EDGE_168","target":"EDGE_168"},{"source":"EDGE_183","target":"EDGE_167'"},{"source":"EDGE_183","target":"EDGE_93'"},{"source":"EDGE_183'","target":"EDGE_10'"},{"source":"EDGE_150'","target":"EDGE_154"},{"source":"EDGE_150","target":"EDGE_165'"},{"source":"EDGE_150","target":"EDGE_189"},{"source":"EDGE_150","target":"EDGE_65'"},{"source":"EDGE_13'","target":"EDGE_14"},{"source":"EDGE_13'","target":"EDGE_15"},{"source":"EDGE_13","target":"EDGE_124'"},{"source":"EDGE_13","target":"EDGE_200"},{"source":"EDGE_13","target":"EDGE_200'"},{"source":"EDGE_151'","target":"EDGE_154"},{"source":"EDGE_151","target":"EDGE_113'"},{"source":"EDGE_151","target":"EDGE_207"},{"source":"EDGE_151","target":"EDGE_208"},{"source":"EDGE_212","target":"EDGE_251"},{"source":"EDGE_212","target":"EDGE_252"},{"source":"EDGE_212'","target":"EDGE_199'"},{"source":"EDGE_212'","target":"EDGE_211"},{"source":"EDGE_93'","target":"EDGE_79'"},{"source":"EDGE_93'","target":"EDGE_92"},{"source":"EDGE_93","target":"EDGE_183'"},{"source":"EDGE_101'","target":"EDGE_102"},{"source":"EDGE_101","target":"EDGE_227"},{"source":"EDGE_245","target":"EDGE_274"},{"source":"EDGE_245'","target":"EDGE_63'"},{"source":"EDGE_245'","target":"EDGE_68'"},{"source":"EDGE_189'","target":"EDGE_150'"},{"source":"EDGE_189","target":"EDGE_253"},{"source":"EDGE_189","target":"EDGE_38'"},{"source":"EDGE_260'","target":"EDGE_259"},{"source":"EDGE_260'","target":"EDGE_70'"},{"source":"EDGE_260","target":"EDGE_206'"},{"source":"EDGE_260","target":"EDGE_259'"},{"source":"EDGE_273","target":"EDGE_20'"},{"source":"EDGE_273","target":"EDGE_272'"},{"source":"EDGE_273'","target":"EDGE_104'"},{"source":"EDGE_273'","target":"EDGE_272"},{"source":"EDGE_160'","target":"EDGE_102'"},{"source":"EDGE_160'","target":"EDGE_24'"},{"source":"EDGE_160","target":"EDGE_269"},{"source":"EDGE_160","target":"EDGE_270"},{"source":"EDGE_274'","target":"EDGE_228'"},{"source":"EDGE_274'","target":"EDGE_245'"},{"source":"EDGE_274","target":"EDGE_277'"},{"source":"EDGE_274","target":"EDGE_280"},{"source":"EDGE_210'","target":"EDGE_50'"},{"source":"EDGE_210","target":"EDGE_114'"},{"source":"EDGE_210","target":"EDGE_234'"},{"source":"EDGE_185'","target":"EDGE_34'"},{"source":"EDGE_185","target":"EDGE_224'"},{"source":"EDGE_185","target":"EDGE_86'"},{"source":"EDGE_254","target":"EDGE_143'"},{"source":"EDGE_254'","target":"EDGE_255"},{"source":"EDGE_37","target":"EDGE_175'"},{"source":"EDGE_37","target":"EDGE_220"},{"source":"EDGE_37'","target":"EDGE_38"},{"source":"EDGE_37'","target":"EDGE_39"},{"source":"EDGE_37'","target":"EDGE_271'"},{"source":"EDGE_37'","target":"EDGE_271"},{"source":"EDGE_108'","target":"EDGE_106"},{"source":"EDGE_108'","target":"EDGE_107"},{"source":"EDGE_108","target":"EDGE_106'"},{"source":"EDGE_108","target":"EDGE_191"},{"source":"EDGE_108","target":"EDGE_248'"},{"source":"EDGE_108","target":"EDGE_248"},{"source":"EDGE_55'","target":"EDGE_56"},{"source":"EDGE_55'","target":"EDGE_57"},{"source":"EDGE_55","target":"EDGE_10'"},{"source":"EDGE_228'","target":"EDGE_227"},{"source":"EDGE_228","target":"EDGE_274"},{"source":"EDGE_118","target":"EDGE_257"},{"source":"EDGE_118'","target":"EDGE_117"},{"source":"EDGE_234'","target":"EDGE_232"},{"source":"EDGE_234'","target":"EDGE_233"},{"source":"EDGE_234","target":"EDGE_210'"},{"source":"EDGE_255'","target":"EDGE_254"},{"source":"EDGE_255'","target":"EDGE_66'"},{"source":"EDGE_255","target":"EDGE_253'"},{"source":"EDGE_255","target":"EDGE_262"},{"source":"EDGE_38'","target":"EDGE_37"},{"source":"EDGE_38","target":"EDGE_189'"},{"source":"EDGE_188","target":"EDGE_149'"},{"source":"EDGE_188","target":"EDGE_215"},{"source":"EDGE_188'","target":"EDGE_186"},{"source":"EDGE_188'","target":"EDGE_187"},{"source":"EDGE_112","target":"EDGE_213'"},{"source":"EDGE_112'","target":"EDGE_43'"},{"source":"EDGE_29'","target":"EDGE_2'"},{"source":"EDGE_29'","target":"EDGE_30"},{"source":"EDGE_29","target":"EDGE_233'"},{"source":"EDGE_29","target":"EDGE_30'"},{"source":"EDGE_86","target":"EDGE_185'"},{"source":"EDGE_86'","target":"EDGE_84"},{"source":"EDGE_86'","target":"EDGE_85"},{"source":"EDGE_264'","target":"EDGE_262'"},{"source":"EDGE_264'","target":"EDGE_97'"},{"source":"EDGE_264","target":"EDGE_231'"},{"source":"EDGE_7'","target":"EDGE_8"},{"source":"EDGE_7'","target":"EDGE_9"},{"source":"EDGE_7","target":"EDGE_256"},{"source":"EDGE_152","target":"EDGE_242"},{"source":"EDGE_152'","target":"EDGE_154"},{"source":"EDGE_241","target":"EDGE_258'"},{"source":"EDGE_241","target":"EDGE_8'"},{"source":"EDGE_241'","target":"EDGE_221'"},{"source":"EDGE_241'","target":"EDGE_222'"},{"source":"EDGE_5'","target":"EDGE_4"},{"source":"EDGE_5","target":"EDGE_269'"},{"source":"EDGE_5","target":"EDGE_277"},{"source":"EDGE_162'","target":"EDGE_161"},{"source":"EDGE_162","target":"EDGE_111'"},{"source":"EDGE_162","target":"EDGE_179'"},{"source":"EDGE_221'","target":"EDGE_109'"},{"source":"EDGE_221","target":"EDGE_241"},{"source":"EDGE_26","target":"EDGE_124"},{"source":"EDGE_26'","target":"EDGE_28"},{"source":"EDGE_26'","target":"EDGE_266"},{"source":"EDGE_26'","target":"EDGE_266'"},{"source":"EDGE_6","target":"EDGE_270'"},{"source":"EDGE_6","target":"EDGE_280'"},{"source":"EDGE_6'","target":"EDGE_4"},{"source":"EDGE_110'","target":"EDGE_109"},{"source":"EDGE_110","target":"EDGE_145'"},{"source":"EDGE_110","target":"EDGE_163'"},{"source":"EDGE_110","target":"EDGE_163"},{"source":"EDGE_63","target":"EDGE_245"},{"source":"EDGE_63'","target":"EDGE_23'"},{"source":"EDGE_63'","target":"EDGE_64"},{"source":"EDGE_8'","target":"EDGE_7"},{"source":"EDGE_8","target":"EDGE_241'"},{"source":"EDGE_250'","target":"EDGE_197'"},{"source":"EDGE_250'","target":"EDGE_92'"},{"source":"EDGE_250","target":"EDGE_251'"},{"source":"EDGE_250","target":"EDGE_252'"},{"source":"EDGE_87'","target":"EDGE_88"},{"source":"EDGE_87'","target":"EDGE_89"},{"source":"EDGE_87","target":"EDGE_88'"},{"source":"EDGE_87","target":"EDGE_97"},{"source":"EDGE_116'","target":"EDGE_114"},{"source":"EDGE_116'","target":"EDGE_115"},{"source":"EDGE_116","target":"EDGE_49'"},{"source":"EDGE_116","target":"EDGE_229"},{"source":"EDGE_116","target":"EDGE_229'"},{"source":"EDGE_116","target":"EDGE_35"},{"source":"EDGE_116","target":"EDGE_35'"},{"source":"EDGE_216'","target":"EDGE_196'"},{"source":"EDGE_216'","target":"EDGE_51'"},{"source":"EDGE_216","target":"EDGE_31'"},{"source":"EDGE_220'","target":"EDGE_37'"},{"source":"EDGE_220","target":"EDGE_256"},{"source":"EDGE_84","target":"EDGE_125'"},{"source":"EDGE_84","target":"EDGE_197"},{"source":"EDGE_84'","target":"EDGE_86"},{"source":"EDGE_198'","target":"EDGE_146'"},{"source":"EDGE_198","target":"EDGE_180'"},{"source":"EDGE_148'","target":"EDGE_134'"},{"source":"EDGE_148","target":"EDGE_239'"},{"source":"EDGE_60","target":"EDGE_192'"},{"source":"EDGE_60'","target":"EDGE_62"},{"source":"EDGE_60'","target":"EDGE_36'"},{"source":"EDGE_60'","target":"EDGE_36"},{"source":"EDGE_74","target":"EDGE_48'"},{"source":"EDGE_74'","target":"EDGE_73"},{"source":"EDGE_74'","target":"EDGE_214"},{"source":"EDGE_74'","target":"EDGE_214'"},{"source":"EDGE_90","target":"EDGE_91'"},{"source":"EDGE_90'","target":"EDGE_91"},{"source":"EDGE_68'","target":"EDGE_67"},{"source":"EDGE_68","target":"EDGE_245"},{"source":"EDGE_14","target":"EDGE_65"},{"source":"EDGE_14","target":"EDGE_66"},{"source":"EDGE_14'","target":"EDGE_13"},{"source":"EDGE_132'","target":"EDGE_134"},{"source":"EDGE_132","target":"EDGE_144'"},{"source":"EDGE_120'","target":"EDGE_48'"},{"source":"EDGE_120","target":"EDGE_75'"},{"source":"EDGE_17","target":"EDGE_59"},{"source":"EDGE_17'","target":"EDGE_16"},{"source":"EDGE_244'","target":"EDGE_201'"},{"source":"EDGE_244'","target":"EDGE_203'"},{"source":"EDGE_244","target":"EDGE_258"},{"source":"EDGE_244","target":"EDGE_52'"},{"source":"EDGE_65'","target":"EDGE_14'"},{"source":"EDGE_65","target":"EDGE_150'"},{"source":"EDGE_130'","target":"EDGE_131"},{"source":"EDGE_130'","target":"EDGE_27'"},{"source":"EDGE_130","target":"EDGE_155"},{"source":"EDGE_130","target":"EDGE_155'"},{"source":"EDGE_111'","target":"EDGE_109"},{"source":"EDGE_111","target":"EDGE_162'"},{"source":"EDGE_50'","target":"EDGE_49"},{"source":"EDGE_50","target":"EDGE_176'"},{"source":"EDGE_50","target":"EDGE_210"},{"source":"EDGE_215'","target":"EDGE_188'"},{"source":"EDGE_215","target":"EDGE_239"},{"source":"EDGE_30'","target":"EDGE_29"},{"source":"EDGE_30","target":"EDGE_29'"},{"source":"EDGE_173'","target":"EDGE_175"},{"source":"EDGE_173","target":"EDGE_218'"},{"source":"EDGE_88","target":"EDGE_87'"},{"source":"EDGE_88'","target":"EDGE_87"},{"source":"EDGE_106","target":"EDGE_108'"},{"source":"EDGE_106'","target":"EDGE_108"},{"source":"EDGE_109","target":"EDGE_221"},{"source":"EDGE_109","target":"EDGE_222"},{"source":"EDGE_109'","target":"EDGE_110"},{"source":"EDGE_109'","target":"EDGE_111"},{"source":"EDGE_143","target":"EDGE_238'"},{"source":"EDGE_143","target":"EDGE_254'"},{"source":"EDGE_143'","target":"EDGE_142"},{"source":"EDGE_143'","target":"EDGE_142'"},{"source":"EDGE_103'","target":"EDGE_105"},{"source":"EDGE_103","target":"EDGE_105'"},{"source":"EDGE_181","target":"EDGE_242'"},{"source":"EDGE_181'","target":"EDGE_180"},{"source":"EDGE_149'","target":"EDGE_134'"},{"source":"EDGE_149","target":"EDGE_188'"},{"source":"EDGE_231","target":"EDGE_223'"},{"source":"EDGE_231","target":"EDGE_264'"},{"source":"EDGE_231'","target":"EDGE_230"},{"source":"EDGE_9","target":"EDGE_144"},{"source":"EDGE_9'","target":"EDGE_7"},{"source":"EDGE_145","target":"EDGE_110'"},{"source":"EDGE_145","target":"EDGE_170"},{"source":"EDGE_145'","target":"EDGE_144"},{"source":"EDGE_237'","target":"EDGE_235"},{"source":"EDGE_237'","target":"EDGE_236"},{"source":"EDGE_237","target":"EDGE_133'"},{"source":"EDGE_237","target":"EDGE_263'"},{"source":"EDGE_174'","target":"EDGE_175"},{"source":"EDGE_174","target":"EDGE_257"},{"source":"EDGE_265","target":"EDGE_257'"},{"source":"EDGE_265'","target":"EDGE_218'"},{"source":"EDGE_113'","target":"EDGE_43'"},{"source":"EDGE_113","target":"EDGE_151'"},{"source":"EDGE_225","target":"EDGE_239'"},{"source":"EDGE_225'","target":"EDGE_72'"},{"source":"EDGE_182'","target":"EDGE_180"},{"source":"EDGE_182","target":"EDGE_242'"},{"source":"EDGE_239","target":"EDGE_148'"},{"source":"EDGE_239","target":"EDGE_225'"},{"source":"EDGE_239'","target":"EDGE_215'"},{"source":"EDGE_239'","target":"EDGE_238"},{"source":"EDGE_155","target":"EDGE_130'"},{"source":"EDGE_155'","target":"EDGE_130'"},{"source":"EDGE_253","target":"EDGE_255'"},{"source":"EDGE_253'","target":"EDGE_189'"},{"source":"EDGE_135'","target":"EDGE_16'"},{"source":"EDGE_135","target":"EDGE_59'"},{"source":"EDGE_64","target":"EDGE_240"},{"source":"EDGE_64'","target":"EDGE_63"},{"source":"EDGE_263'","target":"EDGE_256'"},{"source":"EDGE_263","target":"EDGE_237'"},{"source":"EDGE_176'","target":"EDGE_115'"},{"source":"EDGE_176","target":"EDGE_50'"},{"source":"EDGE_158","target":"EDGE_157'"},{"source":"EDGE_158'","target":"EDGE_157"},{"source":"EDGE_199'","target":"EDGE_146'"},{"source":"EDGE_199","target":"EDGE_212"},{"source":"EDGE_141","target":"EDGE_85'"},{"source":"EDGE_141","target":"EDGE_94'"},{"source":"EDGE_141'","target":"EDGE_139"},{"source":"EDGE_141'","target":"EDGE_140"},{"source":"EDGE_278","target":"EDGE_32'"},{"source":"EDGE_278","target":"EDGE_57'"},{"source":"EDGE_278'","target":"EDGE_139'"},{"source":"EDGE_278'","target":"EDGE_42'"},{"source":"EDGE_91'","target":"EDGE_89'"},{"source":"EDGE_91'","target":"EDGE_90"},{"source":"EDGE_91","target":"EDGE_127"},{"source":"EDGE_91","target":"EDGE_90'"},{"source":"EDGE_49'","target":"EDGE_50"},{"source":"EDGE_49'","target":"EDGE_51"},{"source":"EDGE_49","target":"EDGE_116'"},{"source":"EDGE_49","target":"EDGE_156"},{"source":"EDGE_203'","target":"EDGE_157'"},{"source":"EDGE_203","target":"EDGE_244"},{"source":"EDGE_119","target":"EDGE_146'"},{"source":"EDGE_119'","target":"EDGE_117"},{"source":"EDGE_218'","target":"EDGE_123'"},{"source":"EDGE_218","target":"EDGE_173'"},{"source":"EDGE_218","target":"EDGE_265"},{"source":"EDGE_56","target":"EDGE_126"},{"source":"EDGE_56'","target":"EDGE_55"},{"source":"EDGE_165'","target":"EDGE_164"},{"source":"EDGE_165","target":"EDGE_150'"},{"source":"EDGE_207","target":"EDGE_124'"},{"source":"EDGE_207'","target":"EDGE_151'"},{"source":"EDGE_104'","target":"EDGE_105"},{"source":"EDGE_104","target":"EDGE_273"},{"source":"EDGE_222","target":"EDGE_241"},{"source":"EDGE_222'","target":"EDGE_109'"},{"source":"EDGE_201","target":"EDGE_244"},{"source":"EDGE_201'","target":"EDGE_39'"},{"source":"EDGE_142","target":"EDGE_143"},{"source":"EDGE_142'","target":"EDGE_143"},{"source":"EDGE_59'","target":"EDGE_17'"},{"source":"EDGE_59'","target":"EDGE_58"},{"source":"EDGE_59","target":"EDGE_135'"},{"source":"EDGE_59","target":"EDGE_18'"},{"source":"EDGE_186'","target":"EDGE_188"},{"source":"EDGE_186","target":"EDGE_205'"},{"source":"EDGE_72","target":"EDGE_225"},{"source":"EDGE_72","target":"EDGE_226"},{"source":"EDGE_72'","target":"EDGE_70"},{"source":"EDGE_72'","target":"EDGE_71"},{"source":"EDGE_205'","target":"EDGE_153'"},{"source":"EDGE_205","target":"EDGE_170'"},{"source":"EDGE_205","target":"EDGE_186'"},{"source":"EDGE_153'","target":"EDGE_154"},{"source":"EDGE_153","target":"EDGE_205"},{"source":"EDGE_153","target":"EDGE_206"},{"source":"EDGE_170","target":"EDGE_205'"},{"source":"EDGE_170'","target":"EDGE_145'"},{"source":"EDGE_70'","target":"EDGE_72"},{"source":"EDGE_70","target":"EDGE_260"},{"source":"EDGE_267","target":"EDGE_138'"},{"source":"EDGE_267'","target":"EDGE_126'"},{"source":"EDGE_208","target":"EDGE_123'"},{"source":"EDGE_208'","target":"EDGE_151'"},{"source":"EDGE_123'","target":"EDGE_124"},{"source":"EDGE_123","target":"EDGE_208'"},{"source":"EDGE_123","target":"EDGE_218"},{"source":"EDGE_275'","target":"EDGE_122'"},{"source":"EDGE_275","target":"EDGE_246'"},{"source":"EDGE_52","target":"EDGE_244'"},{"source":"EDGE_52'","target":"EDGE_54"},{"source":"EDGE_204'","target":"EDGE_11'"},{"source":"EDGE_204","target":"EDGE_223"},{"source":"EDGE_204","target":"EDGE_224"},{"source":"EDGE_11'","target":"EDGE_12"},{"source":"EDGE_11","target":"EDGE_171'"},{"source":"EDGE_11","target":"EDGE_204"},{"source":"EDGE_12","target":"EDGE_209"},{"source":"EDGE_12","target":"EDGE_67'"},{"source":"EDGE_12'","target":"EDGE_10"},{"source":"EDGE_12'","target":"EDGE_11"},{"source":"EDGE_67'","target":"EDGE_68"},{"source":"EDGE_67'","target":"EDGE_69"},{"source":"EDGE_67","target":"EDGE_12'"},{"source":"EDGE_69","target":"EDGE_102"},{"source":"EDGE_69'","target":"EDGE_67"},{"source":"EDGE_66'","target":"EDGE_14'"},{"source":"EDGE_66","target":"EDGE_255"},{"source":"EDGE_32","target":"EDGE_278'"},{"source":"EDGE_32'","target":"EDGE_34"},{"source":"EDGE_261","target":"EDGE_249'"},{"source":"EDGE_261'","target":"EDGE_180'"},{"source":"EDGE_133'","target":"EDGE_134"},{"source":"EDGE_133","target":"EDGE_237'"},{"source":"EDGE_259'","target":"EDGE_260"},{"source":"EDGE_259","target":"EDGE_260'"},{"source":"EDGE_53","target":"EDGE_257'"},{"source":"EDGE_53'","target":"EDGE_54"},{"source":"EDGE_194'","target":"EDGE_193"},{"source":"EDGE_194","target":"EDGE_15'"},{"source":"EDGE_194","target":"EDGE_19'"},{"source":"EDGE_1","target":"EDGE_3'"},{"source":"EDGE_1'","target":"EDGE_3"},{"source":"EDGE_276'","target":"EDGE_122'"},{"source":"EDGE_276","target":"EDGE_246'"},{"source":"EDGE_211'","target":"EDGE_212"},{"source":"EDGE_211","target":"EDGE_246"},{"source":"EDGE_206'","target":"EDGE_153'"},{"source":"EDGE_206","target":"EDGE_260'"},{"source":"EDGE_71'","target":"EDGE_72"},{"source":"EDGE_71","target":"EDGE_247'"},{"source":"EDGE_2","target":"EDGE_29"},{"source":"EDGE_2'","target":"EDGE_3"},{"source":"EDGE_124'","target":"EDGE_123"},{"source":"EDGE_124'","target":"EDGE_26'"},{"source":"EDGE_124","target":"EDGE_13'"},{"source":"EDGE_124","target":"EDGE_207'"},{"source":"EDGE_121","target":"EDGE_184'"},{"source":"EDGE_121'","target":"EDGE_82'"},{"source":"EDGE_235'","target":"EDGE_237"},{"source":"EDGE_235","target":"EDGE_96'"},{"source":"EDGE_98'","target":"EDGE_100"},{"source":"EDGE_98","target":"EDGE_161"},{"source":"EDGE_226'","target":"EDGE_72'"},{"source":"EDGE_226","target":"EDGE_242"},{"source":"EDGE_187'","target":"EDGE_188"},{"source":"EDGE_187","target":"EDGE_190"},{"source":"EDGE_137'","target":"EDGE_41'"},{"source":"EDGE_137","target":"EDGE_126'"},{"source":"EDGE_89","target":"EDGE_91"},{"source":"EDGE_89'","target":"EDGE_87"},{"source":"EDGE_18'","target":"EDGE_16"},{"source":"EDGE_18","target":"EDGE_59'"},{"source":"EDGE_78'","target":"EDGE_80"},{"source":"EDGE_78","target":"EDGE_164"},{"source":"EDGE_16","target":"EDGE_135"},{"source":"EDGE_16","target":"EDGE_136"},{"source":"EDGE_16'","target":"EDGE_17"},{"source":"EDGE_16'","target":"EDGE_18"},{"source":"EDGE_105'","target":"EDGE_103"},{"source":"EDGE_105'","target":"EDGE_104"},{"source":"EDGE_105","target":"EDGE_103'"},{"source":"EDGE_105","target":"EDGE_191'"},{"source":"EDGE_242","target":"EDGE_181'"},{"source":"EDGE_242","target":"EDGE_182'"},{"source":"EDGE_242'","target":"EDGE_152'"},{"source":"EDGE_242'","target":"EDGE_226'"},{"source":"EDGE_249","target":"EDGE_195'"},{"source":"EDGE_249","target":"EDGE_261'"},{"source":"EDGE_249'","target":"EDGE_107'"},{"source":"EDGE_249'","target":"EDGE_127'"},{"source":"EDGE_257","target":"EDGE_265'"},{"source":"EDGE_257","target":"EDGE_53'"},{"source":"EDGE_257'","target":"EDGE_118'"},{"source":"EDGE_257'","target":"EDGE_174'"},{"source":"EDGE_180'","target":"EDGE_181"},{"source":"EDGE_180'","target":"EDGE_182"},{"source":"EDGE_180","target":"EDGE_198'"},{"source":"EDGE_180","target":"EDGE_261"},{"source":"EDGE_80","target":"EDGE_46'"},{"source":"EDGE_80'","target":"EDGE_78"},{"source":"EDGE_80'","target":"EDGE_79"},{"source":"EDGE_82","target":"EDGE_121"},{"source":"EDGE_82","target":"EDGE_122"},{"source":"EDGE_82'","target":"EDGE_81"},{"source":"EDGE_230'","target":"EDGE_231"},{"source":"EDGE_230'","target":"EDGE_81'"},{"source":"EDGE_230","target":"EDGE_96'"},{"source":"EDGE_122","target":"EDGE_275"},{"source":"EDGE_122","target":"EDGE_276"},{"source":"EDGE_122'","target":"EDGE_82'"},{"source":"EDGE_129","target":"EDGE_128'"},{"source":"EDGE_129","target":"EDGE_140'"},{"source":"EDGE_129'","target":"EDGE_128"},{"source":"EDGE_129'","target":"EDGE_83'"},{"source":"EDGE_128'","target":"EDGE_129"},{"source":"EDGE_128","target":"EDGE_129'"},{"source":"EDGE_24","target":"EDGE_160"},{"source":"EDGE_24'","target":"EDGE_25"},{"source":"EDGE_39","target":"EDGE_201"},{"source":"EDGE_39","target":"EDGE_202"},{"source":"EDGE_39'","target":"EDGE_37"},{"source":"EDGE_28","target":"EDGE_146'"},{"source":"EDGE_28'","target":"EDGE_26"},{"source":"EDGE_28'","target":"EDGE_27"},{"source":"EDGE_146'","target":"EDGE_144"},{"source":"EDGE_146","target":"EDGE_119'"},{"source":"EDGE_146","target":"EDGE_198"},{"source":"EDGE_146","target":"EDGE_199"},{"source":"EDGE_146","target":"EDGE_28'"},{"source":"EDGE_126'","target":"EDGE_125"},{"source":"EDGE_126'","target":"EDGE_56'"},{"source":"EDGE_126","target":"EDGE_137'"},{"source":"EDGE_126","target":"EDGE_267"},{"source":"EDGE_117","target":"EDGE_256'"},{"source":"EDGE_117'","target":"EDGE_118"},{"source":"EDGE_117'","target":"EDGE_119"},{"source":"EDGE_134","target":"EDGE_148"},{"source":"EDGE_134","target":"EDGE_149"},{"source":"EDGE_134'","target":"EDGE_132"},{"source":"EDGE_134'","target":"EDGE_133"},{"source":"EDGE_41","target":"EDGE_137"},{"source":"EDGE_41","target":"EDGE_138"},{"source":"EDGE_41'","target":"EDGE_40"},{"source":"EDGE_138","target":"EDGE_267'"},{"source":"EDGE_138","target":"EDGE_99'"},{"source":"EDGE_138'","target":"EDGE_41'"},{"source":"EDGE_166","target":"EDGE_172"},{"source":"EDGE_166'","target":"EDGE_167"},{"source":"EDGE_166'","target":"EDGE_40'"},{"source":"EDGE_172","target":"EDGE_46'"},{"source":"EDGE_172'","target":"EDGE_166'"},{"source":"EDGE_172'","target":"EDGE_171"},{"source":"EDGE_40","target":"EDGE_166"},{"source":"EDGE_40'","target":"EDGE_41"},{"source":"EDGE_40'","target":"EDGE_42"},{"source":"EDGE_256'","target":"EDGE_220'"},{"source":"EDGE_256'","target":"EDGE_7'"},{"source":"EDGE_256","target":"EDGE_117'"},{"source":"EDGE_256","target":"EDGE_263"},{"source":"EDGE_251","target":"EDGE_250'"},{"source":"EDGE_251'","target":"EDGE_212'"},{"source":"EDGE_252","target":"EDGE_250'"},{"source":"EDGE_252'","target":"EDGE_212'"},{"source":"EDGE_81'","target":"EDGE_82"},{"source":"EDGE_81'","target":"EDGE_83"},{"source":"EDGE_81","target":"EDGE_230"},{"source":"EDGE_131","target":"EDGE_147'"},{"source":"EDGE_131'","target":"EDGE_130"},{"source":"EDGE_280'","target":"EDGE_274'"},{"source":"EDGE_280","target":"EDGE_6'"},{"source":"EDGE_269","target":"EDGE_5'"},{"source":"EDGE_269'","target":"EDGE_160'"},{"source":"EDGE_236'","target":"EDGE_237"},{"source":"EDGE_236","target":"EDGE_247"},{"source":"EDGE_192","target":"EDGE_268"},{"source":"EDGE_192","target":"EDGE_60'"},{"source":"EDGE_192'","target":"EDGE_73'"},{"source":"EDGE_19'","target":"EDGE_20"},{"source":"EDGE_19'","target":"EDGE_21"},{"source":"EDGE_19","target":"EDGE_194'"},{"source":"EDGE_99","target":"EDGE_138'"},{"source":"EDGE_99'","target":"EDGE_100"},{"source":"EDGE_277'","target":"EDGE_5'"},{"source":"EDGE_277","target":"EDGE_274'"},{"source":"EDGE_270'","target":"EDGE_160'"},{"source":"EDGE_270","target":"EDGE_6'"},{"source":"EDGE_178","target":"EDGE_100'"},{"source":"EDGE_178'","target":"EDGE_156'"},{"source":"EDGE_27'","target":"EDGE_28"},{"source":"EDGE_27","target":"EDGE_130"},{"source":"EDGE_232'","target":"EDGE_234"},{"source":"EDGE_232'","target":"EDGE_232"},{"source":"EDGE_247'","target":"EDGE_190'"},{"source":"EDGE_247'","target":"EDGE_236'"},{"source":"EDGE_247","target":"EDGE_164'"},{"source":"EDGE_247","target":"EDGE_54'"},{"source":"EDGE_247","target":"EDGE_71'"},{"source":"EDGE_190'","target":"EDGE_161'"},{"source":"EDGE_190'","target":"EDGE_187'"},{"source":"EDGE_190","target":"EDGE_247"},{"source":"EDGE_217'","target":"EDGE_184'"},{"source":"EDGE_217","target":"EDGE_279"},{"source":"EDGE_217","target":"EDGE_279'"},{"source":"EDGE_184'","target":"EDGE_147'"},{"source":"EDGE_184","target":"EDGE_121'"},{"source":"EDGE_184","target":"EDGE_217"},{"source":"EDGE_147'","target":"EDGE_144"},{"source":"EDGE_147","target":"EDGE_131'"},{"source":"EDGE_147","target":"EDGE_184"},{"source":"EDGE_279","target":"EDGE_217'"},{"source":"EDGE_279'","target":"EDGE_217'"},{"source":"EDGE_144","target":"EDGE_132'"},{"source":"EDGE_144","target":"EDGE_154'"},{"source":"EDGE_144'","target":"EDGE_145"},{"source":"EDGE_144'","target":"EDGE_146"},{"source":"EDGE_144'","target":"EDGE_147"},{"source":"EDGE_144'","target":"EDGE_9'"},{"source":"EDGE_281","target":"EDGE_281"},{"source":"EDGE_281'","target":"EDGE_281'"},{"source":"EDGE_45","target":"EDGE_202'"},{"source":"EDGE_45","target":"EDGE_213"},{"source":"EDGE_45'","target":"EDGE_43"},{"source":"EDGE_45'","target":"EDGE_44"},{"source":"EDGE_213","target":"EDGE_112'"},{"source":"EDGE_213","target":"EDGE_44'"},{"source":"EDGE_213'","target":"EDGE_45'"},{"source":"EDGE_34'","target":"EDGE_31"},{"source":"EDGE_34'","target":"EDGE_32"},{"source":"EDGE_34'","target":"EDGE_33"},{"source":"EDGE_34","target":"EDGE_185"},{"source":"EDGE_34","target":"EDGE_58'"},{"source":"EDGE_75'","target":"EDGE_73"},{"source":"EDGE_75","target":"EDGE_120'"},{"source":"EDGE_75","target":"EDGE_47'"},{"source":"EDGE_240'","target":"EDGE_227'"},{"source":"EDGE_240'","target":"EDGE_64'"},{"source":"EDGE_240","target":"EDGE_209'"},{"source":"EDGE_209","target":"EDGE_240'"},{"source":"EDGE_209","target":"EDGE_25'"},{"source":"EDGE_209'","target":"EDGE_12'"},{"source":"EDGE_227'","target":"EDGE_101'"},{"source":"EDGE_227'","target":"EDGE_228"},{"source":"EDGE_227","target":"EDGE_240"},{"source":"EDGE_62'","target":"EDGE_60"},{"source":"EDGE_62'","target":"EDGE_61"},{"source":"EDGE_62","target":"EDGE_4'"},{"source":"EDGE_61","target":"EDGE_73'"},{"source":"EDGE_61'","target":"EDGE_62"},{"source":"EDGE_268'","target":"EDGE_192'"},{"source":"EDGE_268","target":"EDGE_4'"},{"source":"EDGE_243'","target":"EDGE_243'"},{"source":"EDGE_243","target":"EDGE_243"},{"source":"EDGE_272","target":"EDGE_273'"},{"source":"EDGE_272'","target":"EDGE_273"},{"source":"EDGE_42'","target":"EDGE_40"},{"source":"EDGE_42","target":"EDGE_278"},{"source":"EDGE_258'","target":"EDGE_244'"},{"source":"EDGE_258","target":"EDGE_241'"},{"source":"EDGE_58","target":"EDGE_34'"},{"source":"EDGE_58'","target":"EDGE_59"},{"source":"EDGE_197","target":"EDGE_250"},{"source":"EDGE_197'","target":"EDGE_84'"},{"source":"EDGE_94'","target":"EDGE_96"},{"source":"EDGE_94","target":"EDGE_141'"},{"source":"EDGE_33'","target":"EDGE_34"},{"source":"EDGE_33","target":"EDGE_193"},{"source":"EDGE_159'","target":"EDGE_157"},{"source":"EDGE_159","target":"EDGE_95'"},{"source":"EDGE_25'","target":"EDGE_23"},{"source":"EDGE_25'","target":"EDGE_24"},{"source":"EDGE_25","target":"EDGE_209'"},{"source":"EDGE_171'","target":"EDGE_172"},{"source":"EDGE_171","target":"EDGE_11'"},{"source":"EDGE_114'","target":"EDGE_116"},{"source":"EDGE_114","target":"EDGE_210'"},{"source":"EDGE_177'","target":"EDGE_115'"},{"source":"EDGE_177","target":"EDGE_31'"},{"source":"EDGE_83'","target":"EDGE_81"},{"source":"EDGE_83","target":"EDGE_129"},{"source":"EDGE_47'","target":"EDGE_46"},{"source":"EDGE_47","target":"EDGE_75'"},{"source":"EDGE_195'","target":"EDGE_193"},{"source":"EDGE_195","target":"EDGE_249'"},{"source":"EDGE_262","target":"EDGE_264"},{"source":"EDGE_262'","target":"EDGE_255'"},{"source":"EDGE_139","target":"EDGE_278"},{"source":"EDGE_139'","target":"EDGE_141"},{"source":"EDGE_57","target":"EDGE_278'"},{"source":"EDGE_57'","target":"EDGE_55"},{"source":"EDGE_238'","target":"EDGE_239"},{"source":"EDGE_238","target":"EDGE_143'"},{"source":"EDGE_115'","target":"EDGE_116"},{"source":"EDGE_115","target":"EDGE_176"},{"source":"EDGE_115","target":"EDGE_177"},{"source":"EDGE_48'","target":"EDGE_46"},{"source":"EDGE_48","target":"EDGE_120"},{"source":"EDGE_48","target":"EDGE_74'"},{"source":"EDGE_95","target":"EDGE_159'"},{"source":"EDGE_95","target":"EDGE_193'"},{"source":"EDGE_95'","target":"EDGE_96"},{"source":"EDGE_193'","target":"EDGE_194"},{"source":"EDGE_193'","target":"EDGE_195"},{"source":"EDGE_193'","target":"EDGE_196"},{"source":"EDGE_193'","target":"EDGE_33'"},{"source":"EDGE_193","target":"EDGE_95'"},{"source":"EDGE_196","target":"EDGE_216"},{"source":"EDGE_196'","target":"EDGE_193"},{"source":"EDGE_100","target":"EDGE_178'"},{"source":"EDGE_100","target":"EDGE_219'"},{"source":"EDGE_100'","target":"EDGE_98"},{"source":"EDGE_100'","target":"EDGE_99"},{"source":"EDGE_246","target":"EDGE_275'"},{"source":"EDGE_246","target":"EDGE_276'"},{"source":"EDGE_246'","target":"EDGE_211'"},{"source":"EDGE_246'","target":"EDGE_21'"},{"source":"EDGE_96","target":"EDGE_230'"},{"source":"EDGE_96","target":"EDGE_235'"},{"source":"EDGE_96'","target":"EDGE_94"},{"source":"EDGE_96'","target":"EDGE_95"},{"source":"EDGE_20'","target":"EDGE_19"},{"source":"EDGE_20","target":"EDGE_273'"},{"source":"EDGE_51'","target":"EDGE_49"},{"source":"EDGE_51","target":"EDGE_216"},{"source":"EDGE_223'","target":"EDGE_204'"},{"source":"EDGE_223","target":"EDGE_231'"},{"source":"EDGE_107'","target":"EDGE_108"},{"source":"EDGE_107","target":"EDGE_249"},{"source":"EDGE_191'","target":"EDGE_108'"},{"source":"EDGE_191","target":"EDGE_105'"},{"source":"EDGE_164","target":"EDGE_247'"},{"source":"EDGE_164'","target":"EDGE_165"},{"source":"EDGE_164'","target":"EDGE_78'"},{"source":"EDGE_140","target":"EDGE_129'"},{"source":"EDGE_140'","target":"EDGE_141"},{"source":"EDGE_97","target":"EDGE_264"},{"source":"EDGE_97'","target":"EDGE_87'"},{"source":"EDGE_224'","target":"EDGE_204'"},{"source":"EDGE_224","target":"EDGE_185'"},{"source":"EDGE_179'","target":"EDGE_156'"},{"source":"EDGE_179","target":"EDGE_162'"},{"source":"EDGE_15","target":"EDGE_194'"},{"source":"EDGE_15'","target":"EDGE_13"},{"source":"EDGE_167'","target":"EDGE_166"},{"source":"EDGE_167","target":"EDGE_183'"},{"source":"EDGE_92'","target":"EDGE_93"},{"source":"EDGE_92","target":"EDGE_250"},{"source":"EDGE_46","target":"EDGE_172'"},{"source":"EDGE_46","target":"EDGE_80'"},{"source":"EDGE_46'","target":"EDGE_47"},{"source":"EDGE_46'","target":"EDGE_48"},{"source":"EDGE_154'","target":"EDGE_150"},{"source":"EDGE_154'","target":"EDGE_151"},{"source":"EDGE_154'","target":"EDGE_152"},{"source":"EDGE_154'","target":"EDGE_153"},{"source":"EDGE_154","target":"EDGE_144'"},{"source":"EDGE_85","target":"EDGE_141'"},{"source":"EDGE_85'","target":"EDGE_86"},{"source":"EDGE_127'","target":"EDGE_91'"},{"source":"EDGE_127","target":"EDGE_249"},{"source":"EDGE_219","target":"EDGE_100'"},{"source":"EDGE_219","target":"EDGE_219'"},{"source":"EDGE_79","target":"EDGE_93"},{"source":"EDGE_79'","target":"EDGE_80"},{"source":"EDGE_233","target":"EDGE_29'"},{"source":"EDGE_233'","target":"EDGE_234"},{"source":"EDGE_73","target":"EDGE_192"},{"source":"EDGE_73","target":"EDGE_61'"},{"source":"EDGE_73'","target":"EDGE_74"},{"source":"EDGE_73'","target":"EDGE_75"},{"source":"EDGE_21'","target":"EDGE_19"},{"source":"EDGE_21","target":"EDGE_246"},{"source":"EDGE_125","target":"EDGE_84'"},{"source":"EDGE_125'","target":"EDGE_126"},{"source":"EDGE_136'","target":"EDGE_16'"},{"source":"EDGE_136","target":"EDGE_3'"},{"source":"EDGE_44'","target":"EDGE_45"},{"source":"EDGE_44","target":"EDGE_213'"},{"source":"EDGE_202'","target":"EDGE_39'"},{"source":"EDGE_202","target":"EDGE_45'"},{"source":"EDGE_4'","target":"EDGE_5"},{"source":"EDGE_4'","target":"EDGE_6"},{"source":"EDGE_4","target":"EDGE_268'"},{"source":"EDGE_4","target":"EDGE_62'"}],"nodes":[{"id":"EDGE_10"},{"id":"EDGE_10'"},{"id":"EDGE_31"},{"id":"EDGE_31'"},{"id":"EDGE_3"},{"id":"EDGE_3'"},{"id":"EDGE_22'"},{"id":"EDGE_22"},{"id":"EDGE_23'"},{"id":"EDGE_23"},{"id":"EDGE_77"},{"id":"EDGE_77'"},{"id":"EDGE_76"},{"id":"EDGE_76'"},{"id":"EDGE_54"},{"id":"EDGE_54'"},{"id":"EDGE_43"},{"id":"EDGE_43'"},{"id":"EDGE_102'"},{"id":"EDGE_102"},{"id":"EDGE_157"},{"id":"EDGE_157'"},{"id":"EDGE_161"},{"id":"EDGE_161'"},{"id":"EDGE_156"},{"id":"EDGE_156'"},{"id":"EDGE_169"},{"id":"EDGE_169'"},{"id":"EDGE_175"},{"id":"EDGE_175'"},{"id":"EDGE_168'"},{"id":"EDGE_168"},{"id":"EDGE_183"},{"id":"EDGE_183'"},{"id":"EDGE_150'"},{"id":"EDGE_150"},{"id":"EDGE_13'"},{"id":"EDGE_13"},{"id":"EDGE_200"},{"id":"EDGE_200'"},{"id":"EDGE_151'"},{"id":"EDGE_151"},{"id":"EDGE_212"},{"id":"EDGE_212'"},{"id":"EDGE_93'"},{"id":"EDGE_93"},{"id":"EDGE_101'"},{"id":"EDGE_101"},{"id":"EDGE_245"},{"id":"EDGE_245'"},{"id":"EDGE_189'"},{"id":"EDGE_189"},{"id":"EDGE_260'"},{"id":"EDGE_260"},{"id":"EDGE_273"},{"id":"EDGE_273'"},{"id":"EDGE_160'"},{"id":"EDGE_160"},{"id":"EDGE_274'"},{"id":"EDGE_274"},{"id":"EDGE_210'"},{"id":"EDGE_210"},{"id":"EDGE_185'"},{"id":"EDGE_185"},{"id":"EDGE_254"},{"id":"EDGE_254'"},{"id":"EDGE_37"},{"id":"EDGE_37'"},{"id":"EDGE_271'"},{"id":"EDGE_271"},{"id":"EDGE_108'"},{"id":"EDGE_108"},{"id":"EDGE_248'"},{"id":"EDGE_248"},{"id":"EDGE_55'"},{"id":"EDGE_55"},{"id":"EDGE_228'"},{"id":"EDGE_228"},{"id":"EDGE_118"},{"id":"EDGE_118'"},{"id":"EDGE_234'"},{"id":"EDGE_234"},{"id":"EDGE_255'"},{"id":"EDGE_255"},{"id":"EDGE_38'"},{"id":"EDGE_38"},{"id":"EDGE_188"},{"id":"EDGE_188'"},{"id":"EDGE_112"},{"id":"EDGE_112'"},{"id":"EDGE_29'"},{"id":"EDGE_29"},{"id":"EDGE_86"},{"id":"EDGE_86'"},{"id":"EDGE_264'"},{"id":"EDGE_264"},{"id":"EDGE_7'"},{"id":"EDGE_7"},{"id":"EDGE_152"},{"id":"EDGE_152'"},{"id":"EDGE_241"},{"id":"EDGE_241'"},{"id":"EDGE_5'"},{"id":"EDGE_5"},{"id":"EDGE_162'"},{"id":"EDGE_162"},{"id":"EDGE_221'"},{"id":"EDGE_221"},{"id":"EDGE_26"},{"id":"EDGE_26'"},{"id":"EDGE_266"},{"id":"EDGE_266'"},{"id":"EDGE_6"},{"id":"EDGE_6'"},{"id":"EDGE_110'"},{"id":"EDGE_110"},{"id":"EDGE_163'"},{"id":"EDGE_163"},{"id":"EDGE_63"},{"id":"EDGE_63'"},{"id":"EDGE_8'"},{"id":"EDGE_8"},{"id":"EDGE_250'"},{"id":"EDGE_250"},{"id":"EDGE_87'"},{"id":"EDGE_87"},{"id":"EDGE_116'"},{"id":"EDGE_116"},{"id":"EDGE_229"},{"id":"EDGE_229'"},{"id":"EDGE_35"},{"id":"EDGE_35'"},{"id":"EDGE_216'"},{"id":"EDGE_216"},{"id":"EDGE_220'"},{"id":"EDGE_220"},{"id":"EDGE_84"},{"id":"EDGE_84'"},{"id":"EDGE_198'"},{"id":"EDGE_198"},{"id":"EDGE_148'"},{"id":"EDGE_148"},{"id":"EDGE_60"},{"id":"EDGE_60'"},{"id":"EDGE_36'"},{"id":"EDGE_36"},{"id":"EDGE_74"},{"id":"EDGE_74'"},{"id":"EDGE_214"},{"id":"EDGE_214'"},{"id":"EDGE_90"},{"id":"EDGE_90'"},{"id":"EDGE_68'"},{"id":"EDGE_68"},{"id":"EDGE_14"},{"id":"EDGE_14'"},{"id":"EDGE_132'"},{"id":"EDGE_132"},{"id":"EDGE_120'"},{"id":"EDGE_120"},{"id":"EDGE_17"},{"id":"EDGE_17'"},{"id":"EDGE_244'"},{"id":"EDGE_244"},{"id":"EDGE_65'"},{"id":"EDGE_65"},{"id":"EDGE_130'"},{"id":"EDGE_130"},{"id":"EDGE_111'"},{"id":"EDGE_111"},{"id":"EDGE_50'"},{"id":"EDGE_50"},{"id":"EDGE_215'"},{"id":"EDGE_215"},{"id":"EDGE_30'"},{"id":"EDGE_30"},{"id":"EDGE_173'"},{"id":"EDGE_173"},{"id":"EDGE_88"},{"id":"EDGE_88'"},{"id":"EDGE_106"},{"id":"EDGE_106'"},{"id":"EDGE_109"},{"id":"EDGE_109'"},{"id":"EDGE_143"},{"id":"EDGE_143'"},{"id":"EDGE_103'"},{"id":"EDGE_103"},{"id":"EDGE_181"},{"id":"EDGE_181'"},{"id":"EDGE_149'"},{"id":"EDGE_149"},{"id":"EDGE_231"},{"id":"EDGE_231'"},{"id":"EDGE_9"},{"id":"EDGE_9'"},{"id":"EDGE_145"},{"id":"EDGE_145'"},{"id":"EDGE_237'"},{"id":"EDGE_237"},{"id":"EDGE_174'"},{"id":"EDGE_174"},{"id":"EDGE_265"},{"id":"EDGE_265'"},{"id":"EDGE_113'"},{"id":"EDGE_113"},{"id":"EDGE_225"},{"id":"EDGE_225'"},{"id":"EDGE_182'"},{"id":"EDGE_182"},{"id":"EDGE_239"},{"id":"EDGE_239'"},{"id":"EDGE_155"},{"id":"EDGE_155'"},{"id":"EDGE_253"},{"id":"EDGE_253'"},{"id":"EDGE_135'"},{"id":"EDGE_135"},{"id":"EDGE_64"},{"id":"EDGE_64'"},{"id":"EDGE_263'"},{"id":"EDGE_263"},{"id":"EDGE_176'"},{"id":"EDGE_176"},{"id":"EDGE_158"},{"id":"EDGE_158'"},{"id":"EDGE_199'"},{"id":"EDGE_199"},{"id":"EDGE_141"},{"id":"EDGE_141'"},{"id":"EDGE_278"},{"id":"EDGE_278'"},{"id":"EDGE_91'"},{"id":"EDGE_91"},{"id":"EDGE_49'"},{"id":"EDGE_49"},{"id":"EDGE_203'"},{"id":"EDGE_203"},{"id":"EDGE_119"},{"id":"EDGE_119'"},{"id":"EDGE_218'"},{"id":"EDGE_218"},{"id":"EDGE_56"},{"id":"EDGE_56'"},{"id":"EDGE_165'"},{"id":"EDGE_165"},{"id":"EDGE_207"},{"id":"EDGE_207'"},{"id":"EDGE_104'"},{"id":"EDGE_104"},{"id":"EDGE_222"},{"id":"EDGE_222'"},{"id":"EDGE_201"},{"id":"EDGE_201'"},{"id":"EDGE_142"},{"id":"EDGE_142'"},{"id":"EDGE_59'"},{"id":"EDGE_59"},{"id":"EDGE_186'"},{"id":"EDGE_186"},{"id":"EDGE_72"},{"id":"EDGE_72'"},{"id":"EDGE_205'"},{"id":"EDGE_205"},{"id":"EDGE_153'"},{"id":"EDGE_153"},{"id":"EDGE_170"},{"id":"EDGE_170'"},{"id":"EDGE_70'"},{"id":"EDGE_70"},{"id":"EDGE_267"},{"id":"EDGE_267'"},{"id":"EDGE_208"},{"id":"EDGE_208'"},{"id":"EDGE_123'"},{"id":"EDGE_123"},{"id":"EDGE_275'"},{"id":"EDGE_275"},{"id":"EDGE_52"},{"id":"EDGE_52'"},{"id":"EDGE_204'"},{"id":"EDGE_204"},{"id":"EDGE_11'"},{"id":"EDGE_11"},{"id":"EDGE_12"},{"id":"EDGE_12'"},{"id":"EDGE_67'"},{"id":"EDGE_67"},{"id":"EDGE_69"},{"id":"EDGE_69'"},{"id":"EDGE_66'"},{"id":"EDGE_66"},{"id":"EDGE_32"},{"id":"EDGE_32'"},{"id":"EDGE_261"},{"id":"EDGE_261'"},{"id":"EDGE_133'"},{"id":"EDGE_133"},{"id":"EDGE_259'"},{"id":"EDGE_259"},{"id":"EDGE_53"},{"id":"EDGE_53'"},{"id":"EDGE_194'"},{"id":"EDGE_194"},{"id":"EDGE_1"},{"id":"EDGE_1'"},{"id":"EDGE_276'"},{"id":"EDGE_276"},{"id":"EDGE_211'"},{"id":"EDGE_211"},{"id":"EDGE_206'"},{"id":"EDGE_206"},{"id":"EDGE_71'"},{"id":"EDGE_71"},{"id":"EDGE_2"},{"id":"EDGE_2'"},{"id":"EDGE_124'"},{"id":"EDGE_124"},{"id":"EDGE_121"},{"id":"EDGE_121'"},{"id":"EDGE_235'"},{"id":"EDGE_235"},{"id":"EDGE_98'"},{"id":"EDGE_98"},{"id":"EDGE_226'"},{"id":"EDGE_226"},{"id":"EDGE_187'"},{"id":"EDGE_187"},{"id":"EDGE_137'"},{"id":"EDGE_137"},{"id":"EDGE_89"},{"id":"EDGE_89'"},{"id":"EDGE_18'"},{"id":"EDGE_18"},{"id":"EDGE_78'"},{"id":"EDGE_78"},{"id":"EDGE_16"},{"id":"EDGE_16'"},{"id":"EDGE_105'"},{"id":"EDGE_105"},{"id":"EDGE_242"},{"id":"EDGE_242'"},{"id":"EDGE_249"},{"id":"EDGE_249'"},{"id":"EDGE_257"},{"id":"EDGE_257'"},{"id":"EDGE_180'"},{"id":"EDGE_180"},{"id":"EDGE_80"},{"id":"EDGE_80'"},{"id":"EDGE_82"},{"id":"EDGE_82'"},{"id":"EDGE_230'"},{"id":"EDGE_230"},{"id":"EDGE_122"},{"id":"EDGE_122'"},{"id":"EDGE_129"},{"id":"EDGE_129'"},{"id":"EDGE_128'"},{"id":"EDGE_128"},{"id":"EDGE_24"},{"id":"EDGE_24'"},{"id":"EDGE_39"},{"id":"EDGE_39'"},{"id":"EDGE_28"},{"id":"EDGE_28'"},{"id":"EDGE_146'"},{"id":"EDGE_146"},{"id":"EDGE_126'"},{"id":"EDGE_126"},{"id":"EDGE_117"},{"id":"EDGE_117'"},{"id":"EDGE_134"},{"id":"EDGE_134'"},{"id":"EDGE_41"},{"id":"EDGE_41'"},{"id":"EDGE_138"},{"id":"EDGE_138'"},{"id":"EDGE_166"},{"id":"EDGE_166'"},{"id":"EDGE_172"},{"id":"EDGE_172'"},{"id":"EDGE_40"},{"id":"EDGE_40'"},{"id":"EDGE_256'"},{"id":"EDGE_256"},{"id":"EDGE_251"},{"id":"EDGE_251'"},{"id":"EDGE_252"},{"id":"EDGE_252'"},{"id":"EDGE_81'"},{"id":"EDGE_81"},{"id":"EDGE_131"},{"id":"EDGE_131'"},{"id":"EDGE_280'"},{"id":"EDGE_280"},{"id":"EDGE_269"},{"id":"EDGE_269'"},{"id":"EDGE_236'"},{"id":"EDGE_236"},{"id":"EDGE_192"},{"id":"EDGE_192'"},{"id":"EDGE_19'"},{"id":"EDGE_19"},{"id":"EDGE_99"},{"id":"EDGE_99'"},{"id":"EDGE_277'"},{"id":"EDGE_277"},{"id":"EDGE_270'"},{"id":"EDGE_270"},{"id":"EDGE_178"},{"id":"EDGE_178'"},{"id":"EDGE_27'"},{"id":"EDGE_27"},{"id":"EDGE_232'"},{"id":"EDGE_232"},{"id":"EDGE_247'"},{"id":"EDGE_247"},{"id":"EDGE_190'"},{"id":"EDGE_190"},{"id":"EDGE_217'"},{"id":"EDGE_217"},{"id":"EDGE_184'"},{"id":"EDGE_184"},{"id":"EDGE_147'"},{"id":"EDGE_147"},{"id":"EDGE_279"},{"id":"EDGE_279'"},{"id":"EDGE_144"},{"id":"EDGE_144'"},{"id":"EDGE_281"},{"id":"EDGE_281'"},{"id":"EDGE_45"},{"id":"EDGE_45'"},{"id":"EDGE_213"},{"id":"EDGE_213'"},{"id":"EDGE_34'"},{"id":"EDGE_34"},{"id":"EDGE_75'"},{"id":"EDGE_75"},{"id":"EDGE_240'"},{"id":"EDGE_240"},{"id":"EDGE_209"},{"id":"EDGE_209'"},{"id":"EDGE_227'"},{"id":"EDGE_227"},{"id":"EDGE_62'"},{"id":"EDGE_62"},{"id":"EDGE_61"},{"id":"EDGE_61'"},{"id":"EDGE_268'"},{"id":"EDGE_268"},{"id":"EDGE_243'"},{"id":"EDGE_243"},{"id":"EDGE_272"},{"id":"EDGE_272'"},{"id":"EDGE_42'"},{"id":"EDGE_42"},{"id":"EDGE_258'"},{"id":"EDGE_258"},{"id":"EDGE_58"},{"id":"EDGE_58'"},{"id":"EDGE_197"},{"id":"EDGE_197'"},{"id":"EDGE_94'"},{"id":"EDGE_94"},{"id":"EDGE_33'"},{"id":"EDGE_33"},{"id":"EDGE_159'"},{"id":"EDGE_159"},{"id":"EDGE_25'"},{"id":"EDGE_25"},{"id":"EDGE_171'"},{"id":"EDGE_171"},{"id":"EDGE_114'"},{"id":"EDGE_114"},{"id":"EDGE_177'"},{"id":"EDGE_177"},{"id":"EDGE_83'"},{"id":"EDGE_83"},{"id":"EDGE_47'"},{"id":"EDGE_47"},{"id":"EDGE_195'"},{"id":"EDGE_195"},{"id":"EDGE_262"},{"id":"EDGE_262'"},{"id":"EDGE_139"},{"id":"EDGE_139'"},{"id":"EDGE_57"},{"id":"EDGE_57'"},{"id":"EDGE_238'"},{"id":"EDGE_238"},{"id":"EDGE_115'"},{"id":"EDGE_115"},{"id":"EDGE_48'"},{"id":"EDGE_48"},{"id":"EDGE_95"},{"id":"EDGE_95'"},{"id":"EDGE_193'"},{"id":"EDGE_193"},{"id":"EDGE_196"},{"id":"EDGE_196'"},{"id":"EDGE_100"},{"id":"EDGE_100'"},{"id":"EDGE_246"},{"id":"EDGE_246'"},{"id":"EDGE_96"},{"id":"EDGE_96'"},{"id":"EDGE_20'"},{"id":"EDGE_20"},{"id":"EDGE_51'"},{"id":"EDGE_51"},{"id":"EDGE_223'"},{"id":"EDGE_223"},{"id":"EDGE_107'"},{"id":"EDGE_107"},{"id":"EDGE_191'"},{"id":"EDGE_191"},{"id":"EDGE_164"},{"id":"EDGE_164'"},{"id":"EDGE_140"},{"id":"EDGE_140'"},{"id":"EDGE_97"},{"id":"EDGE_97'"},{"id":"EDGE_224'"},{"id":"EDGE_224"},{"id":"EDGE_179'"},{"id":"EDGE_179"},{"id":"EDGE_15"},{"id":"EDGE_15'"},{"id":"EDGE_167'"},{"id":"EDGE_167"},{"id":"EDGE_92'"},{"id":"EDGE_92"},{"id":"EDGE_46"},{"id":"EDGE_46'"},{"id":"EDGE_154'"},{"id":"EDGE_154"},{"id":"EDGE_85"},{"id":"EDGE_85'"},{"id":"EDGE_127'"},{"id":"EDGE_127"},{"id":"EDGE_219"},{"id":"EDGE_219'"},{"id":"EDGE_79"},{"id":"EDGE_79'"},{"id":"EDGE_233"},{"id":"EDGE_233'"},{"id":"EDGE_73"},{"id":"EDGE_73'"},{"id":"EDGE_21'"},{"id":"EDGE_21"},{"id":"EDGE_125"},{"id":"EDGE_125'"},{"id":"EDGE_136'"},{"id":"EDGE_136"},{"id":"EDGE_44'"},{"id":"EDGE_44"},{"id":"EDGE_202'"},{"id":"EDGE_202"},{"id":"EDGE_4'"},{"id":"EDGE_4"}]}